topsis_aarzoo_102303061/__init__.py
topsis_aarzoo_102303061/topsis.py
topsis_aarzoo_102303061-1.0.0.dist-info/licenses/LICENSE
topsis_aarzoo_102303061-1.0.0.dist-info/METADATA
topsis_aarzoo_102303061-1.0.0.dist-info/WHEEL
topsis_aarzoo_102303061-1.0.0.dist-info/entry_points.txt
topsis_aarzoo_102303061-1.0.0.dist-info/top_level.txt
topsis_aarzoo_102303061-1.0.0.dist-info/RECORD
