Metadata-Version: 2.4
Name: topsis-aarzoo-102303061
Version: 1.0.0
Summary: A Python package for TOPSIS multi-criteria decision making
Author: Aarzoo
Author-email: aarzoo@example.com
Classifier: Programming Language :: Python :: 3
Classifier: License :: OSI Approved :: MIT License
Classifier: Operating System :: OS Independent
Requires-Python: >=3.6
License-File: LICENSE
Requires-Dist: pandas
Requires-Dist: numpy
Dynamic: author
Dynamic: author-email
Dynamic: classifier
Dynamic: description
Dynamic: description-content-type
Dynamic: license-file
Dynamic: requires-dist
Dynamic: requires-python
Dynamic: summary
